polylith_cli/polylith/alias/__init__.py
polylith_cli/polylith/alias/core.py
polylith_cli/polylith/bricks/__init__.py
polylith_cli/polylith/bricks/base.py
polylith_cli/polylith/bricks/brick.py
polylith_cli/polylith/bricks/component.py
polylith_cli/polylith/building/__init__.py
polylith_cli/polylith/building/core.py
polylith_cli/polylith/building/paths.py
polylith_cli/polylith/check/__init__.py
polylith_cli/polylith/check/collect.py
polylith_cli/polylith/check/grouping.py
polylith_cli/polylith/check/report.py
polylith_cli/polylith/cli/__init__.py
polylith_cli/polylith/cli/__main__.py
polylith_cli/polylith/cli/build.py
polylith_cli/polylith/cli/core.py
polylith_cli/polylith/cli/create.py
polylith_cli/polylith/cli/env.py
polylith_cli/polylith/cli/options.py
polylith_cli/polylith/cli/test.py
polylith_cli/polylith/commands/__init__.py
polylith_cli/polylith/commands/check.py
polylith_cli/polylith/commands/create.py
polylith_cli/polylith/commands/deps.py
polylith_cli/polylith/commands/diff.py
polylith_cli/polylith/commands/info.py
polylith_cli/polylith/commands/libs.py
polylith_cli/polylith/commands/sync.py
polylith_cli/polylith/commands/test.py
polylith_cli/polylith/configuration/__init__.py
polylith_cli/polylith/configuration/core.py
polylith_cli/polylith/deps/__init__.py
polylith_cli/polylith/deps/core.py
polylith_cli/polylith/deps/report.py
polylith_cli/polylith/development/__init__.py
polylith_cli/polylith/development/development.py
polylith_cli/polylith/diff/__init__.py
polylith_cli/polylith/diff/collect.py
polylith_cli/polylith/diff/report.py
polylith_cli/polylith/dirs/__init__.py
polylith_cli/polylith/dirs/dirs.py
polylith_cli/polylith/distributions/__init__.py
polylith_cli/polylith/distributions/caching.py
polylith_cli/polylith/distributions/collect.py
polylith_cli/polylith/distributions/core.py
polylith_cli/polylith/environment/__init__.py
polylith_cli/polylith/environment/core.py
polylith_cli/polylith/files/__init__.py
polylith_cli/polylith/files/files.py
polylith_cli-1.41.1.dist-info/METADATA
polylith_cli-1.41.1.dist-info/WHEEL
polylith_cli-1.41.1.dist-info/entry_points.txt
polylith_cli-1.41.1.dist-info/RECORD
