Metadata-Version: 2.4
Name: polylith-cli
Version: 1.41.1
Summary: Python tooling support for the Polylith Architecture
License: MIT
Author: David Vujic
Requires-Python: >=3.8,<4.0
Classifier: License :: OSI Approved :: MIT License
Classifier: Programming Language :: Python :: 3
Classifier: Programming Language :: Python :: 3.8
Classifier: Programming Language :: Python :: 3.9
Classifier: Programming Language :: Python :: 3.10
Classifier: Programming Language :: Python :: 3.11
Classifier: Programming Language :: Python :: 3.12
Classifier: Programming Language :: Python :: 3.13
Classifier: Programming Language :: Python :: 3.14
Requires-Dist: pyyaml
Requires-Dist: rich (>=13,<15)
Requires-Dist: tomlkit (==0.*)
Requires-Dist: typer (==0.*)
Project-URL: Homepage, https://davidvujic.github.io/python-polylith-docs/
Project-URL: Repository, https://github.com/davidvujic/python-polylith
